Metadata-Version: 2.1
Name: twitter-auto-post-bot
Version: 1.0.0
Summary: A python library to tweet or post content on twitter automatically.
Home-page: https://twitter-api.datakund.com/en/latest/
Author: DataKund
Author-email: datakund@gmail.com
License: Apache License 2.0
Keywords: twitter python bot_studio automation login post content tweet
Platform: UNKNOWN
